autodatap/__init__.py
autodatap/main.py
libname/__init__.py
libname/main.py
autodatap-1.5.2.dist-info/METADATA
autodatap-1.5.2.dist-info/WHEEL
autodatap-1.5.2.dist-info/entry_points.txt
autodatap-1.5.2.dist-info/top_level.txt
autodatap-1.5.2.dist-info/RECORD
