Metadata-Version: 2.1
Name: autodatap
Version: 1.5.2
Summary: Automating Data Preprocessing
Author: SyabAhmad
Keywords: python,machine learning,data science,data,preprocessing,AI
Classifier: Development Status :: 1 - Planning
Classifier: Intended Audience :: Developers
Classifier: Programming Language :: Python :: 2.7
Classifier: Operating System :: Unix
Classifier: Operating System :: MacOS :: MacOS X
Classifier: Operating System :: Microsoft :: Windows
Requires-Dist: pandas
Requires-Dist: scikit-learn
Requires-Dist: chardet
